{"type":"PR","pr":{"number":5,"head":"7862651a34c06d3bd6382a74762b1c4951845a4b"},"user":"suige787","status":"pending_publish","branch":"cms/【cssだけ】formのラベルを動かす","collection":"blog","title":"【CSSだけ】Formのラベルを動かす","description":"フォームのInputタグをクリックした際に、プレイスホルダーのようなラベルが上に動くアニメーション。プレスホルダーに見せかけて、実はラベルを使っています。\n本当はJavaScriptを使ってクラス名を変更するほうがどの環境でも使用できると思います。","objects":{"entry":{"path":"src/pages/blog/【cssだけ】formのラベルを動かす.md","sha":"e830bb819b36c4e4a61505bab40afe9c1ee4060d"},"files":[{"path":"/static/img/floatlabelform.gif","sha":"670596d4321c11946423f1e017cd42bef405b5cc"}]},"timeStamp":"2018-09-28T06:03:38.697Z"}